lammpsio/__init__.py
lammpsio/_compatibility.py
lammpsio/box.py
lammpsio/data.py
lammpsio/dump.py
lammpsio/snapshot.py
lammpsio/topology.py
lammpsio-0.7.0.dist-info/LICENSE
lammpsio-0.7.0.dist-info/METADATA
lammpsio-0.7.0.dist-info/WHEEL
lammpsio-0.7.0.dist-info/top_level.txt
lammpsio-0.7.0.dist-info/RECORD
