Metadata-Version: 2.1
Name: lammpsio
Version: 0.7.0
Summary: Python tools for working with LAMMPS
Home-page: https://github.com/mphowardlab/lammpsio
Author: Michael P. Howard
Author-email: mphoward@auburn.edu
Project-URL: Source Code, https://github.com/mphowardlab/lammpsio
Project-URL: Issue Tracker, https://github.com/mphowardlab/lammpsio/issues
Classifier: Intended Audience :: Science/Research
Classifier: License :: OSI Approved :: BSD License
Classifier: Topic :: Scientific/Engineering :: Chemistry
Classifier: Topic :: Scientific/Engineering :: Physics
Classifier: Programming Language :: Python :: 3.9
Classifier: Programming Language :: Python :: 3.10
Classifier: Programming Language :: Python :: 3.11
Classifier: Programming Language :: Python :: 3.12
Classifier: Programming Language :: Python :: 3.13
Requires-Python: >=3.9
License-File: LICENSE
Requires-Dist: numpy
Requires-Dist: packaging
